MANIFEST.in
README.rst
setup.py
docs/HISTORY.txt
docs/INSTALL.txt
docs/LICENSE.GPL
docs/LICENSE.txt
docs/TODO.txt
unice/.DS_Store
unice/__init__.py
unice.portlet.lettre.egg-info/PKG-INFO
unice.portlet.lettre.egg-info/SOURCES.txt
unice.portlet.lettre.egg-info/dependency_links.txt
unice.portlet.lettre.egg-info/entry_points.txt
unice.portlet.lettre.egg-info/namespace_packages.txt
unice.portlet.lettre.egg-info/not-zip-safe
unice.portlet.lettre.egg-info/requires.txt
unice.portlet.lettre.egg-info/top_level.txt
unice/portlet/.DS_Store
unice/portlet/__init__.py
unice/portlet/lettre/.DS_Store
unice/portlet/lettre/__init__.py
unice/portlet/lettre/configure.zcml
unice/portlet/lettre/lettreportlet.pt
unice/portlet/lettre/lettreportlet.py
unice/portlet/lettre/vocabularies.py
unice/portlet/lettre/browser/.DS_Store
unice/portlet/lettre/browser/__init__.py
unice/portlet/lettre/browser/configure.zcml
unice/portlet/lettre/browser/stylesheets/styles.css
unice/portlet/lettre/browser/stylesheets/styles.less
unice/portlet/lettre/profiles/.DS_Store
unice/portlet/lettre/profiles/default/cssregistry.xml
unice/portlet/lettre/profiles/default/metadata.xml
unice/portlet/lettre/profiles/default/portlets.xml
unice/portlet/lettre/tests/__init__.py
unice/portlet/lettre/tests/base.py
unice/portlet/lettre/tests/test_portlet.py